Workbook

Sheet Warehouse Proforma
A1: CT Truck and Trailer Shop LLC — Warehouse Lease Proforma
A2: Prepared for ownership review — August 27, 2026
A4: 1. LEASE ASSUMPTIONS (WHAT WE'RE COMMITTING TO)
A5: Total leased space (SF) | B5: 5700
A6: Lease rate ($/SF/month) | B6: 0.89
A7: Monthly lease cost | B7: =$B$5*$B$6 -> 5073
A8: Annual lease cost | B8: =$B$7*12 -> 60876
A9: Suite 5 at 3550 W Clarendon Ave (Thomas Industrial Plaza), 5,700 SF per the confirmed listing, $0.89/SF/mo Modified Gross.
A10: Additional SF from racking (0 until racking is installed) | B10: 0
A11: Total available capacity (leased floor + racking) | B11: =$B$5+$B$10 -> 5700
A12: Racking adds usable capacity, not leased footprint, so lease cost above is unaffected. Set to 0 until racking is installed; once installed, perimeter racking at 3 levels (4'-deep rows on 3 walls, ~925 SF racked footprint) adds an estimated ~1,850 SF effective capacity.
A13: Assumed occupancy — realistic ramp across all space (not just SBA) | B13: 0.75
A14: Usable SF at assumed occupancy | B14: =($B$5*$B$13)+$B$10 -> 4275
A15: Occupancy applies only to the base leased SF (e.g. at 75% of 5,700 SF, 4,275 SF is assumed occupied). Racking-added SF is included at full value, not discounted — racking is capacity you're building specifically to use, not floor space assumed to sit partly vacant. SBA's contracted allocation is drawn from this combined pool in Section 3.
A17: 2. YEAR 1 LEASE PAYMENT RAMP (FREE RENT / ABATEMENT CONCESSION)
A18: Concession being negotiated: months 1-3 free, months 4-8 at half rate, month 9 onward at full rate. Applies to Year 1 only — Year 2+ reverts to the full monthly lease cost from Section 1.
B19: Rent Factor | C19: Months | D19: Payment (period)
A20: Months 1-3 (free rent) | B20: 0 | C20: 3 | D20: =3*$B$7*$B$20 -> 0
A21: Months 4-8 (half rate) | B21: 0.5 | C21: 5 | D21: =5*$B$7*$B$21 -> 12682.5
A22: Months 9-12 (full rate) | B22: 1 | C22: 4 | D22: =4*$B$7*$B$22 -> 20292
A23: Total Year 1 lease cost (with concession) | D23: =$D$20+$D$21+$D$22 -> 32974.5
A24: Reference: full-rate annual lease cost (no concession, Year 2+) | D24: =$B$8 -> 60876
A25: Year 1 savings from concession | D25: =$B$8-$D$23 -> 27901.5
A26: Effective average monthly lease cost — Year 1 | D26: =$D$23/12 -> 2747.875
A27: This average smooths the ramp across 12 months for margin comparison in Section 6 — actual monthly cash outlay is $0 in months 1-3, half in months 4-6, full from month 7 on, not this flat average.
A29: 3. CURRENT (BRIDGE) REVENUE — SBA PALLET AGREEMENT
A30: Signed agreement, per-pallet/day rate; reflects short-notice accommodation, not the target ongoing model.
A31: Pallets currently on site | B31: 24
A32: Rate per pallet per day | B32: 50
A33: Bridge revenue per day | B33: =$B$31*$B$32 -> 1200
A34: Bridge revenue per month (x30 days) | B34: =$B$31*$B$32*30 -> 36000
A35: Note: this rate is fixed only for these 24 pallets while they remain on site — treat as temporary, not a repeatable revenue base.
A37: 4. TARGET STEADY-STATE REVENUE (ONCE SQUARE-FOOT AGREEMENTS ARE IN PLACE)
A38: SBA's allocation and the remaining space below are both drawn from the usable SF at occupancy (Section 1) — not the raw leased SF.
B39: SF Allocated | C39: Rate ($/SF/mo) | D39: Monthly Revenue
A40: SBA — climate-controlled, secured space (contracted) | B40: 2500 | C40: 3 | D40: =$B$40*$C$40 -> 7500
A41: Ad hoc cross-dock revenue (Phoenix Cross Dock, from Section 8 model) | B41: =$B$87 -> 500 | D41: =$B$75 -> 17500
A42: B41 shows the implied pallets/month from Section 8 needed to hit this revenue — not a SF-based calculation. This replaces the old placeholder that assumed a hypothetical second SF-lease tenant.
A43: Revenue is sourced entirely from Section 8's real published fee-schedule rates ($25/pallet cross-dock, dwell fees) applied against David's 30% SBA / 70% ad hoc revenue split assumption — not a generic market-rate guess.
A44: Realistic steady-state revenue (SBA + remaining, at occupancy) | D44: =$D$40+$D$41 -> 25000
A45: Reference: full-capacity scenario not separately modeled under the ad hoc approach — see Section 8/9 for pallet-volume sensitivity | D45: =$D$44 -> 25000
A47: 5. ESTIMATED OPERATING EXPENSES (BEYOND LEASE)
A48: Placeholder estimates — not yet quoted. Replace with real numbers before finalizing.
A49: Property/goods-in-care insurance (monthly est.) | B49: 300
A50: Utilities (monthly est.) | B50: 250
A51: Security/surveillance system (monthly est.) | B51: 150
A52: Labor / admin overhead allocation (monthly est.) | B52: 1500
A53: Total monthly operating expenses (excl. lease) | B53: =$B$49+$B$50+$B$51+$B$52 -> 2200
A55: 6. NET MARGIN SUMMARY
B56: Bridge (Current) | C56: Steady-State (Full) | D56: Steady-State (Adj. Occ.) | E56: Year 1 (w/ Lease Ramp)
A57: Monthly revenue | B57: =$B$34 -> 36000 | C57: =$D$45 -> 25000 | D57: =$D$44 -> 25000 | E57: ='Monthly Forecast'!$B$20/12 -> 18437.5
A58: Less: monthly lease cost | B58: =-$B$7 -> -5073 | C58: =-$B$7 -> -5073 | D58: =-$B$7 -> -5073 | E58: =-$D$26 -> -2747.875
A59: Less: monthly operating expenses | B59: =-$B$53 -> -2200 | C59: =-$B$53 -> -2200 | D59: =-$B$53 -> -2200 | E59: =-$B$53 -> -2200
A60: Net monthly margin | B60: =B57+B58+B59 -> 28727 | C60: =C57+C58+C59 -> 17727 | D60: =D57+D58+D59 -> 17727 | E60: =E57+E58+E59 -> 13489.625
A61: Net annual margin (x12) | B61: =B60*12 -> 344724 | C61: =C60*12 -> 212724 | D61: =D60*12 -> 212724 | E61: =E60*12 -> 161875.5
A62: Margin as % of revenue | B62: =IFERROR(B60/B57,0) -> 0.79797222 | C62: =IFERROR(C60/C57,0) -> 0.70908 | D62: =IFERROR(D60/D57,0) -> 0.70908 | E62: =IFERROR(E60/E57,0) -> 0.73164068
A63: "Year 1 (w/ Lease Ramp)" now pulls its monthly average directly from the Monthly Forecast tab, which ramps remaining-space revenue up to the occupancy target over 9 months rather than assuming it's full from day 1 — so this column reflects a realistic lease-up, not just the lease concession alone.
A65: 7. BREAKEVEN
A66: % of Section 8 ad hoc revenue needed to cover any shortfall after SBA | B66: =MAX(0,IFERROR(($B$7+$B$53-$D$40)/$B$75,0)) -> 0
A67: If this shows 0%, SBA alone already covers the full lease + operating costs — all Section 8 ad hoc revenue is pure margin on top, not needed to break even.
A69: 8. PHOENIX CROSS DOCK — AD HOC REVENUE MODEL (SEPARATE BUSINESS FROM SBA CONTRACT)
A70: Phoenix Cross Dock is a separate ad hoc/walk-in service business (phoenix-crossdock.com) using its own published rate sheet — distinct from the signed SBA contract, which has its own negotiated terms. Models what David's assumed revenue mix implies in practice: if SBA's contracted revenue is only 30% of total, what does the other 70% (Phoenix Cross Dock ad hoc volume) need to look like in actual pallets/loads moved?
A71: SBA contract (locked-in) monthly revenue — from Section 4 | B71: =$D$40 -> 7500
A72: Uses only SBA's signed 2,500 SF allocation — the one revenue source that doesn't compete with Phoenix Cross Dock for floor space. The "remaining space" lease revenue in Section 4 ($1.45/SF customers) is deliberately excluded here, since Section 9 shows that space is needed for cross-dock staging instead — counting both would double-book the same square footage.
A73: Assumed SBA share of total revenue (David's estimate) | B73: 0.3
A74: Implied total monthly revenue (SBA ÷ share) | B74: =IFERROR($B$71/$B$73,0) -> 25000
A75: Implied Phoenix Cross Dock revenue needed (remaining 70%) | B75: =$B$74-$B$71 -> 17500
A77: PHOENIX CROSS DOCK PUBLISHED RATES (per phoenix-crossdock.com DRAFT fee schedule)
A78: Per-pallet cross-dock rate (dry) | B78: 25
A79: Free dwell period (hours) before storage charge starts | B79: 48
A80: Free dwell period (days, converted) | B80: =$B$79/24 -> 2
A81: Dwell rate per pallet per day (after free period) | B81: 10
A82: Phoenix Cross Dock's published range is $8-12/pallet/day after 48h free — $10 used as the working midpoint. SBA's contract now defers to these same standard rates for any volume beyond their dedicated 2,500 SF, so there's no separate custom SBA overflow rate to reconcile — overflow is simply standard Phoenix Cross Dock business.
A83: Assumed average dwell per pallet across the mix (days) | B83: 3
A84: Some pallets move same-day, some sit up to ~7 days — this is a blended average across that mix, not a single scenario. Adjust based on actual customer behavior once observed.
A85: Average billable dwell days (avg dwell minus free period) | B85: =MAX(0,$B$83-$B$80) -> 1
A86: Average revenue per pallet (handling + dwell) | B86: =$B$78+($B$85*$B$81) -> 35
A87: Implied pallets needed / month | B87: =IFERROR($B$75/$B$86,0) -> 500
A88: Implied pallets needed / week | B88: =IFERROR($B$75/$B$86/4.33,0) -> 115.47344
A89: Example at these rates: a pallet dwelling 7 days = $25 handling + (7-2) × $10 dwell = $75 total. A pallet within the 48h free window = $25 flat.
A91: PER-TRAILER RATE (Phoenix Cross Dock published range)
A92: Per-trailer simple transfer rate | B92: 425
A93: Uses Phoenix Cross Dock's own published $350-500/trailer range ($425 midpoint) for messy/mixed loads, rather than deriving from the per-pallet rate — this is their actual quoted price for this service type.
A94: Implied loads needed / month | B94: =IFERROR($B$75/$B$92,0) -> 41.176471
A95: Implied loads needed / week | B95: =IFERROR($B$75/$B$92/4.33,0) -> 9.5095775
A96: Reality check: this listing has 1 dock-high door + 2 roll-up doors. Compare implied loads/week and pallets/week above against realistic door throughput and available labor before treating this split as achievable.
A98: Implied blended net margin at this mix:
A99: Implied total monthly revenue | B99: =$B$74 -> 25000
A100: Less: monthly lease cost | B100: =-$B$7 -> -5073
A101: Less: monthly operating expenses | B101: =-$B$53 -> -2200
A102: Net monthly margin at implied mix | B102: =$B$74-$B$7-$B$53 -> 17727
A103: Net annual margin at implied mix (x12) | B103: =$B$102*12 -> 212724
A105: 9. STAGING SF REQUIRED FOR THIS AD HOC VOLUME (LITTLE'S LAW)
A106: Pallets don't just pass through — some sit for days, so space needed depends on volume AND dwell time together, not volume alone. Avg pallets on floor at once = daily inflow × average dwell days (Little's Law).
A107: Implied pallets needed / day (from Section 8 monthly ÷ 30) | B107: =$B$75/$B$86/30 -> 16.666667
A108: Average pallets on floor at once (daily inflow × avg dwell) | B108: =$B$107*$B$83 -> 50
A109: Max dwell scenario (days) — worst case if flow held at max dwell | B109: 7
A110: Peak pallets on floor at once (daily inflow × max dwell) | B110: =$B$107*$B$109 -> 116.66667
B112: SF / pallet | C112: SF needed (avg) | D112: SF needed (peak)
A113: Dense floor-stacked staging (tight aisles) | B113: 15 | C113: =$B$108*$B$113 -> 750 | D113: =$B$110*$B$113 -> 1750
...

Sheet Pricing Analysis
A1: What to Charge Customers Like SBA — Pricing Analysis
A2: Same warehouse cost basis as the Warehouse Proforma tab.
A4: 1. COST BASIS
A5: Total leased space (SF) | B5: ='Warehouse Proforma'!B5 -> 5700
A6: Monthly lease cost | B6: ='Warehouse Proforma'!B7 -> 5073
A7: Monthly operating expenses | B7: ='Warehouse Proforma'!B53 -> 2200
A8: Total monthly cost (lease + opex) | B8: =$B$6+$B$7 -> 7273
A9: Cost per SF per month, if 100% occupied | B9: =$B$8/$B$5 -> 1.2759649
A11: 2. BREAKEVEN PRICE ($/SF/MONTH) BY HOW MUCH SPACE IS ACTUALLY RENTED
A12: You pay the full lease regardless of fill rate, so the price needed to break even rises as occupancy drops.
A13: Occupancy of leased space | B13: 1 | C13: 0.9 | D13: 0.8 | E13: 0.7 | F13: 0.6 | G13: 0.5
A14: Breakeven price needed ($/SF/mo) | B14: =$B$8/($B$5*B13) -> 1.2759649 | C14: =$B$8/($B$5*C13) -> 1.4177388 | D14: =$B$8/($B$5*D13) -> 1.5949561 | E14: =$B$8/($B$5*E13) -> 1.822807 | F14: =$B$8/($B$5*F13) -> 2.1266082 | G14: =$B$8/($B$5*G13) -> 2.5519298
A16: 3. PRICE NEEDED TO HIT A TARGET MARGIN (AT A GIVEN OCCUPANCY)
A17: Target occupancy assumption | B17: 0.75
A18: Target margin % | B18: 0 | C18: 0.2 | D18: 0.3 | E18: 0.4 | F18: 0.5
A19: Required price ($/SF/mo) | B19: =($B$8/(1-B18))/($B$5*$B$17) -> 1.7012865 | C19: =($B$8/(1-C18))/($B$5*$B$17) -> 2.1266082 | D19: =($B$8/(1-D18))/($B$5*$B$17) -> 2.4304094 | E19: =($B$8/(1-E18))/($B$5*$B$17) -> 2.8354776 | F19: =($B$8/(1-F18))/($B$5*$B$17) -> 3.4025731
A21: 4. MARKET REFERENCE POINTS
A22: Standard dry warehouse storage (general market) | B22: $1.25 – $1.75 / SF / mo
A23: Climate-controlled storage (general market) | B23: roughly $1.25 above standard, wide range
A24: SBA rate under discussion (surveillance + adjacent access) | B24: 3
A25: $3.28/SF is a premium over general market comps — justified by surveillance, and proximity, but worth having ready to explain if a customer benchmarks it.
A27: 5. WHAT THIS MEANS FOR PRICING
A28: At 75% occupancy, breakeven is the value in Section 2 above the 70-80% columns. A price of $1.25–$1.75/SF sits well above breakeven even at 50-60% fill — the real driver of profit here is occupancy, not the last few cents of rate. Premium customers (climate control, security, convenience — like SBA) can reasonably be priced meaningfully above that base, as SBA's own discussion suggests.

Sheet Monthly Forecast
A1: Year 1 Monthly Revenue & Margin Forecast
A2: SBA at full contracted rate from Month 1. Remaining space ramps toward the 75% occupancy target by Month 9 via active marketing.
A4: 1. LEASE-UP ASSUMPTIONS
A5: Months to reach target occupancy (ramp length) | B5: 9
A6: Based on Phoenix small-bay industrial market conditions (Q1 2026): small-bay/flex space under 100,000 SF is running just 4-6% vacancy metro-wide — roughly a third of the big-box vacancy rate — with rents up ~5-6% YoY, indicating strong absorption for space this size. A 9-month lease-up to 75% occupancy is a reasonable, moderately conservative target in this environment with active marketing; adjust if your broker/marketing partner gives a different read.
A8: 2. MONTHLY FORECAST
B9: Month 1 | C9: Month 2 | D9: Month 3 | E9: Month 4 | F9: Month 5 | G9: Month 6 | H9: Month 7 | I9: Month 8 | J9: Month 9 | K9: Month 10 | L9: Month 11 | M9: Month 12
A10: SBA revenue (contracted, from Month 1) | B10: ='Warehouse Proforma'!$D$40 -> 7500 | C10: ='Warehouse Proforma'!$D$40 -> 7500 | D10: ='Warehouse Proforma'!$D$40 -> 7500 | E10: ='Warehouse Proforma'!$D$40 -> 7500 | F10: ='Warehouse Proforma'!$D$40 -> 7500 | G10: ='Warehouse Proforma'!$D$40 -> 7500 | H10: ='Warehouse Proforma'!$D$40 -> 7500 | I10: ='Warehouse Proforma'!$D$40 -> 7500 | ... M10: ='Warehouse Proforma'!$D$40 -> 7500
A11: Ad hoc cross-dock pallets (ramping toward Section 8 target) | B11: =MIN('Warehouse Proforma'!$B$87,'Warehouse Proforma'!$B$87*(1-1)/($B$5-1)) -> 0 | C11: =MIN('Warehouse Proforma'!$B$87,'Warehouse Proforma'!$B$87*(2-1)/($B$5-1)) -> 62.5 | D11: =MIN('Warehouse Proforma'!$B$87,'Warehouse Proforma'!$B$87*(3-1)/($B$5-1)) -> 125 | E11: =MIN('Warehouse Proforma'!$B$87,'Warehouse Proforma'!$B$87*(4-1)/($B$5-1)) -> 187.5 | F11: =MIN('Warehouse Proforma'!$B$87,'Warehouse Proforma'!$B$87*(5-1)/($B$5-1)) -> 250 | G11: =MIN('Warehouse Proforma'!$B$87,'Warehouse Proforma'!$B$87*(6-1)/($B$5-1)) -> 312.5 | H11: =MIN('Warehouse Proforma'!$B$87,'Warehouse Proforma'!$B$87*(7-1)/($B$5-1)) -> 375 | I11: =MIN('Warehouse Proforma'!$B$87,'Warehouse Proforma'!$B$87*(8-1)/($B$5-1)) -> 437.5 | J11: =MIN('Warehouse Proforma'!$B$87,'Warehouse Proforma'!$B$87*(9-1)/($B$5-1)) -> 500 | K11: =MIN('Warehouse Proforma'!$B$87,'Warehouse Proforma'!$B$87*(10-1)/($B$5-1)) -> 500 | L11: =MIN('Warehouse Proforma'!$B$87,'Warehouse Proforma'!$B$87*(11-1)/($B$5-1)) -> 500 | M11: =MIN('Warehouse Proforma'!$B$87,'Warehouse Proforma'!$B$87*(12-1)/($B$5-1)) -> 500
A12: Ad hoc cross-dock revenue (Section 8 rate: handling + dwell) | B12: =B11*'Warehouse Proforma'!$B$86 -> 0 | C12: =C11*'Warehouse Proforma'!$B$86 -> 2187.5 | D12: =D11*'Warehouse Proforma'!$B$86 -> 4375 | E12: =E11*'Warehouse Proforma'!$B$86 -> 6562.5 | F12: =F11*'Warehouse Proforma'!$B$86 -> 8750 | G12: =G11*'Warehouse Proforma'!$B$86 -> 10937.5 | H12: =H11*'Warehouse Proforma'!$B$86 -> 13125 | I12: =I11*'Warehouse Proforma'!$B$86 -> 15312.5 | ... M12: =M11*'Warehouse Proforma'!$B$86 -> 17500
A13: Total monthly revenue | B13: =B10+B12 -> 7500 | C13: =C10+C12 -> 9687.5 | D13: =D10+D12 -> 11875 | E13: =E10+E12 -> 14062.5 | F13: =F10+F12 -> 16250 | G13: =G10+G12 -> 18437.5 | H13: =H10+H12 -> 20625 | I13: =I10+I12 -> 22812.5 | ... M13: =M10+M12 -> 25000
A14: Lease cost (per Year 1 ramp) | B14: =IF(1<=3,0,IF(1<=8,'Warehouse Proforma'!$B$7*'Warehouse Proforma'!$B$21,'Warehouse Proforma'!$B$7*'Warehouse Proforma'!$B$22)) -> 0 | C14: =IF(2<=3,0,IF(2<=8,'Warehouse Proforma'!$B$7*'Warehouse Proforma'!$B$21,'Warehouse Proforma'!$B$7*'Warehouse Proforma'!$B$22)) -> 0 | D14: =IF(3<=3,0,IF(3<=8,'Warehouse Proforma'!$B$7*'Warehouse Proforma'!$B$21,'Warehouse Proforma'!$B$7*'Warehouse Proforma'!$B$22)) -> 0 | E14: =IF(4<=3,0,IF(4<=8,'Warehouse Proforma'!$B$7*'Warehouse Proforma'!$B$21,'Warehouse Proforma'!$B$7*'Warehouse Proforma'!$B$22)) -> 2536.5 | F14: =IF(5<=3,0,IF(5<=8,'Warehouse Proforma'!$B$7*'Warehouse Proforma'!$B$21,'Warehouse Proforma'!$B$7*'Warehouse Proforma'!$B$22)) -> 2536.5 | G14: =IF(6<=3,0,IF(6<=8,'Warehouse Proforma'!$B$7*'Warehouse Proforma'!$B$21,'Warehouse Proforma'!$B$7*'Warehouse Proforma'!$B$22)) -> 2536.5 | H14: =IF(7<=3,0,IF(7<=8,'Warehouse Proforma'!$B$7*'Warehouse Proforma'!$B$21,'Warehouse Proforma'!$B$7*'Warehouse Proforma'!$B$22)) -> 2536.5 | I14: =IF(8<=3,0,IF(8<=8,'Warehouse Proforma'!$B$7*'Warehouse Proforma'!$B$21,'Warehouse Proforma'!$B$7*'Warehouse Proforma'!$B$22)) -> 2536.5 | J14: =IF(9<=3,0,IF(9<=8,'Warehouse Proforma'!$B$7*'Warehouse Proforma'!$B$21,'Warehouse Proforma'!$B$7*'Warehouse Proforma'!$B$22)) -> 5073 | K14: =IF(10<=3,0,IF(10<=8,'Warehouse Proforma'!$B$7*'Warehouse Proforma'!$B$21,'Warehouse Proforma'!$B$7*'Warehouse Proforma'!$B$22)) -> 5073 | L14: =IF(11<=3,0,IF(11<=8,'Warehouse Proforma'!$B$7*'Warehouse Proforma'!$B$21,'Warehouse Proforma'!$B$7*'Warehouse Proforma'!$B$22)) -> 5073 | M14: =IF(12<=3,0,IF(12<=8,'Warehouse Proforma'!$B$7*'Warehouse Proforma'!$B$21,'Warehouse Proforma'!$B$7*'Warehouse Proforma'!$B$22)) -> 5073
A15: Operating expenses | B15: ='Warehouse Proforma'!$B$53 -> 2200 | C15: ='Warehouse Proforma'!$B$53 -> 2200 | D15: ='Warehouse Proforma'!$B$53 -> 2200 | E15: ='Warehouse Proforma'!$B$53 -> 2200 | F15: ='Warehouse Proforma'!$B$53 -> 2200 | G15: ='Warehouse Proforma'!$B$53 -> 2200 | H15: ='Warehouse Proforma'!$B$53 -> 2200 | I15: ='Warehouse Proforma'!$B$53 -> 2200 | ... M15: ='Warehouse Proforma'!$B$53 -> 2200
A16: Net monthly margin | B16: =B13-B14-B15 -> 5300 | C16: =C13-C14-C15 -> 7487.5 | D16: =D13-D14-D15 -> 9675 | E16: =E13-E14-E15 -> 9326 | F16: =F13-F14-F15 -> 11513.5 | G16: =G13-G14-G15 -> 13701 | H16: =H13-H14-H15 -> 15888.5 | I16: =I13-I14-I15 -> 18076 | ... M16: =M13-M14-M15 -> 17727
A17: Cumulative net margin | B17: =B16 -> 5300 | C17: =B17+C16 -> 12787.5 | D17: =C17+D16 -> 22462.5 | E17: =D17+E16 -> 31788.5 | F17: =E17+F16 -> 43302 | G17: =F17+G16 -> 57003 | H17: =G17+H16 -> 72891.5 | I17: =H17+I16 -> 90967.5 | J17: =I17+J16 -> 108694.5 | ... M17: =L17+M16 -> 161875.5
A19: 3. YEAR 1 TOTALS (FROM MONTHLY FORECAST)
A20: Total Year 1 revenue | B20: =SUM(B13:M13) -> 221250
A21: Total Year 1 lease cost | B21: =SUM(B14:M14) -> 32974.5
A22: Total Year 1 operating expenses | B22: =SUM(B15:M15) -> 26400
A23: Total Year 1 net margin | B23: =SUM(B16:M16) -> 161875.5
A25: Change the ramp length in Section 1, or edit assumptions on the Warehouse Proforma tab (SBA rate, remaining-space rate, occupancy target, lease ramp factors) — everything here recalculates automatically.
